B14handtracker/__init__.py
B14handtracker/htmmain.py
handtrackermod-0.0.1.dist-info/LICENCE.txt
handtrackermod-0.0.1.dist-info/METADATA
handtrackermod-0.0.1.dist-info/WHEEL
handtrackermod-0.0.1.dist-info/top_level.txt
handtrackermod-0.0.1.dist-info/RECORD
