Metadata-Version: 2.1
Name: handtrackermod
Version: 0.0.1
Summary: handtracking module
Home-page: 
Author: B14
Author-email: quizzer548@gmail.com
Classifier: Programming Language :: Python :: 3
Classifier: License :: OSI Approved :: MIT License
Classifier: Operating System :: OS Independent
License-File: LICENCE.txt
